README.md
setup.cfg
setup.py
langer/langer.py
langer.egg-info/PKG-INFO
langer.egg-info/SOURCES.txt
langer.egg-info/dependency_links.txt
langer.egg-info/not-zip-safe
langer.egg-info/top_level.txt