Metadata-Version: 1.0
Name: langer
Version: 0.121
Summary: Simple HTML translate tool. (Designed for Flask)
Home-page: UNKNOWN
Author: UNKNOWN
Author-email: va.efimov6@ya.ru
License: UNKNOWN
Platform: UNKNOWN
